{
    "build": {
        "content": [{
            "files": [
                "**/*.md",
                "**/*.yml"
            ],
            "exclude": [
                "**/obj/**",
                "**/includes/**",
                "README.md",
                "LICENSE",
                "LICENSE-CODE",
                "ThirdPartyNotices"
            ]
        }],
        "resource": [{
            "files": [
                "**/*.png",
                "**/*.gif",
                "**/*.jpg"
            ],
            "exclude": [
                "**/obj/**",
                "**/includes/**"
            ]
        }],
        "overwrite": [],
        "externalReference": [],
        "globalMetadata": {
            "layout": "Conceptual",
            "breadcrumb_path": "~/bread/toc.yml",
            "author": "markruss",
            "ms.author": "markruss",
            "ms.prod": "sysinternals",
            "ms.technology": ""
        },
        "fileMetadata": {},
        "template": [],
        "dest": "sysinternals"
    }
}